sqream_blue/__init__.py
sqream_blue/hooks/__init__.py
sqream_blue/hooks/sqream_blue.py
sqream_blue/operators/__init__.py
sqream_blue/operators/sqream_blue.py
airflow_provider_sqream_blue-0.0.13.dist-info/LICENSE
airflow_provider_sqream_blue-0.0.13.dist-info/METADATA
airflow_provider_sqream_blue-0.0.13.dist-info/WHEEL
airflow_provider_sqream_blue-0.0.13.dist-info/entry_points.txt
airflow_provider_sqream_blue-0.0.13.dist-info/top_level.txt
airflow_provider_sqream_blue-0.0.13.dist-info/RECORD
