Metadata-Version: 2.1
Name: airflow-provider-sqream-blue
Version: 0.0.13
Summary: About Apache Airflow - A platform to programmatically author, schedule, and monitor workflows.
Home-page: https://github.com/SQream/apache-airflow-providers-sqream-blue
Author: SQream
Author-email: info@sqream.com
License: Apache License 2.0
Classifier: Programming Language :: Python :: 3.9
Classifier: License :: OSI Approved :: BSD License
Classifier: Operating System :: OS Independent
Classifier: Framework :: Apache Airflow
Classifier: Framework :: Apache Airflow :: Provider
Requires-Python: >=3.9
License-File: LICENSE
Requires-Dist: pysqream-blue >=1.0.42
Requires-Dist: apache-airflow >=2.6
Requires-Dist: apache-airflow-providers-common-sql ==1.3.2
